cucim/VERSION
cucim/__init__.py
cucim/__init__.pyi
cucim/__main__.py
cucim/_misc.py
cucim/_version.py
cucim/time.py
cucim/clara/__init__.py
cucim/clara/_cucim.cpython-310-x86_64-linux-gnu.so
cucim/clara/cli.py
cucim/clara/cucim.kit.cumed@25.06.00.so
cucim/clara/cucim.kit.cuslide@25.06.00.so
cucim/clara/libcucim.so.25
cucim/clara/cache/__init__.py
cucim/clara/converter/tiff.py
cucim/clara/filesystem/__init__.py
cucim/clara/io/__init__.py
cucim/core/__init__.py
cucim/core/operations/__init__.py
cucim/core/operations/color/__init__.py
cucim/core/operations/color/jitter.py
cucim/core/operations/color/stain_normalizer.py
cucim/core/operations/color/kernel/cuda_kernel_source.py
cucim/core/operations/color/tests/test_color_jitter.py
cucim/core/operations/expose/transform.py
cucim/core/operations/expose/tests/test_expose.py
cucim/core/operations/intensity/__init__.py
cucim/core/operations/intensity/normalize.py
cucim/core/operations/intensity/scaling.py
cucim/core/operations/intensity/zoom.py
cucim/core/operations/intensity/kernel/cuda_kernel_source.py
cucim/core/operations/intensity/tests/test_normalize.py
cucim/core/operations/intensity/tests/test_rand_zoom.py
cucim/core/operations/intensity/tests/test_scaling.py
cucim/core/operations/intensity/tests/test_zoom.py
cucim/core/operations/morphology/__init__.py
cucim/core/operations/morphology/_distance_transform.py
cucim/core/operations/morphology/_pba_2d.py
cucim/core/operations/morphology/_pba_3d.py
cucim/core/operations/morphology/cuda/pba_kernels_2d.h
cucim/core/operations/morphology/cuda/pba_kernels_3d.h
cucim/core/operations/morphology/tests/test_distance_transform.py
cucim/core/operations/spatial/__init__.py
cucim/core/operations/spatial/rotate_and_flip.py
cucim/core/operations/spatial/tests/test_flip.py
cucim/core/operations/spatial/tests/test_random_flip.py
cucim/core/operations/spatial/tests/test_random_rotate90.py
cucim/core/operations/spatial/tests/test_rotate90.py
cucim_cu11-25.6.0.dist-info/LICENSE
cucim_cu11-25.6.0.dist-info/LICENSE-3rdparty.md
cucim_cu11-25.6.0.dist-info/METADATA
cucim_cu11-25.6.0.dist-info/WHEEL
cucim_cu11-25.6.0.dist-info/entry_points.txt
cucim_cu11-25.6.0.dist-info/top_level.txt
cucim_cu11-25.6.0.dist-info/RECORD
