Metadata-Version: 2.1
Name: cucim-cu11
Version: 25.6.0
Summary: cuCIM - an extensible toolkit designed to provide GPU accelerated I/O, computer vision & image processing primitives for N-Dimensional images with a focus on biomedical imaging.
Author: NVIDIA Corporation
License: Apache 2.0
Project-URL: Homepage, https://developer.nvidia.com/multidimensional-image-processing
Project-URL: Documentation, https://docs.rapids.ai/api/cucim/stable/
Project-URL: Changelog, https://github.com/rapidsai/cucim/blob/main/CHANGELOG.md
Project-URL: Source, https://github.com/rapidsai/cucim
Project-URL: Tracker, https://github.com/rapidsai/cucim/issues
Classifier: Development Status :: 4 - Beta
Classifier: Intended Audience :: Developers
Classifier: Intended Audience :: Education
Classifier: Intended Audience :: Science/Research
Classifier: Intended Audience :: Healthcare Industry
Classifier: Topic :: Scientific/Engineering
Classifier: Operating System :: POSIX :: Linux
Classifier: Environment :: Console
Classifier: Environment :: GPU :: NVIDIA CUDA :: 11
Classifier: Environment :: GPU :: NVIDIA CUDA :: 12
Classifier: License :: OSI Approved :: Apache Software License
Classifier: Programming Language :: C++
Classifier: Programming Language :: Python
Classifier: Programming Language :: Python :: 3
Requires-Python: >=3.10
License-File: LICENSE
License-File: LICENSE-3rdparty.md
Requires-Dist: click
Requires-Dist: cupy-cuda11x>=12.0.0
Requires-Dist: lazy-loader>=0.4
Requires-Dist: numpy<3.0a0,>=1.23.4
Requires-Dist: scikit-image<0.26.0a0,>=0.19.0
Requires-Dist: scipy>=1.11.2
Provides-Extra: developer
Requires-Dist: black; extra == "developer"
Requires-Dist: isort; extra == "developer"
Requires-Dist: pre-commit; extra == "developer"
Requires-Dist: ruff; extra == "developer"
Provides-Extra: docs
Requires-Dist: ipython; extra == "docs"
Requires-Dist: nbsphinx; extra == "docs"
Requires-Dist: numpydoc>=1.7; extra == "docs"
Requires-Dist: pydata-sphinx-theme; extra == "docs"
Requires-Dist: recommonmark; extra == "docs"
Requires-Dist: sphinx<8.2.0,>=8.0.0; extra == "docs"
Provides-Extra: test
Requires-Dist: matplotlib>=3.7; extra == "test"
Requires-Dist: numpydoc>=1.7; extra == "test"
Requires-Dist: opencv-python-headless>=4.6; extra == "test"
Requires-Dist: pooch>=1.6.0; extra == "test"
Requires-Dist: psutil>=5.8.0; extra == "test"
Requires-Dist: pytest-cov>=2.12.1; extra == "test"
Requires-Dist: pytest-lazy-fixtures>=1.0.0; extra == "test"
Requires-Dist: pytest-xdist; extra == "test"
Requires-Dist: pytest<9.0.0a0,>=7.0.0; extra == "test"
Requires-Dist: pywavelets>=1.6; extra == "test"
Requires-Dist: tifffile>=2022.8.12; extra == "test"
Requires-Dist: imagecodecs>=2021.6.8; platform_machine == "x86_64" and extra == "test"
Requires-Dist: openslide-python>=1.3.0; platform_machine == "x86_64" and extra == "test"
